[{"text":"It","startMs":0,"endMs":139,"timestampMs":70,"confidence":null},{"text":" comes","startMs":186,"endMs":360,"timestampMs":273,"confidence":null},{"text":" down","startMs":395,"endMs":522,"timestampMs":459,"confidence":null},{"text":" to","startMs":557,"endMs":615,"timestampMs":586,"confidence":null},{"text":" three","startMs":685,"endMs":929,"timestampMs":807,"confidence":null},{"text":" questions.","startMs":975,"endMs":1614,"timestampMs":1295,"confidence":null},{"text":" What","startMs":2055,"endMs":2357,"timestampMs":2206,"confidence":null},{"text":" is","startMs":2450,"endMs":2647,"timestampMs":2548,"confidence":null},{"text":" the","startMs":2717,"endMs":2798,"timestampMs":2758,"confidence":null},{"text":" task?","startMs":2856,"endMs":3460,"timestampMs":3158,"confidence":null},{"text":" What","startMs":3901,"endMs":4133,"timestampMs":4017,"confidence":null},{"text":" class","startMs":4203,"endMs":4551,"timestampMs":4377,"confidence":null},{"text":" of","startMs":4586,"endMs":4644,"timestampMs":4615,"confidence":null},{"text":" data","startMs":4714,"endMs":5027,"timestampMs":4871,"confidence":null},{"text":" does","startMs":5085,"endMs":5224,"timestampMs":5155,"confidence":null},{"text":" it","startMs":5271,"endMs":5341,"timestampMs":5306,"confidence":null},{"text":" touch?","startMs":5387,"endMs":5840,"timestampMs":5614,"confidence":null},{"text":" And","startMs":6165,"endMs":6304,"timestampMs":6235,"confidence":null},{"text":" which","startMs":6351,"endMs":6525,"timestampMs":6438,"confidence":null},{"text":" approved","startMs":6560,"endMs":6861,"timestampMs":6711,"confidence":null},{"text":" tool","startMs":6885,"endMs":7082,"timestampMs":6983,"confidence":null},{"text":" is","startMs":7129,"endMs":7187,"timestampMs":7158,"confidence":null},{"text":" cleared","startMs":7233,"endMs":7465,"timestampMs":7349,"confidence":null},{"text":" for","startMs":7500,"endMs":7581,"timestampMs":7541,"confidence":null},{"text":" that","startMs":7616,"endMs":7732,"timestampMs":7674,"confidence":null},{"text":" class?","startMs":7779,"endMs":8290,"timestampMs":8034,"confidence":null},{"text":" Answer","startMs":8800,"endMs":9160,"timestampMs":8980,"confidence":null},{"text":" those","startMs":9218,"endMs":9416,"timestampMs":9317,"confidence":null},{"text":" in","startMs":9462,"endMs":9532,"timestampMs":9497,"confidence":null},{"text":" order","startMs":9613,"endMs":9938,"timestampMs":9776,"confidence":null},{"text":" and","startMs":10031,"endMs":10182,"timestampMs":10107,"confidence":null},{"text":" most","startMs":10263,"endMs":10484,"timestampMs":10374,"confidence":null},{"text":" decisions","startMs":10542,"endMs":11041,"timestampMs":10792,"confidence":null},{"text":" make","startMs":11134,"endMs":11366,"timestampMs":11250,"confidence":null},{"text":" themselves.","startMs":11401,"endMs":12307,"timestampMs":11854,"confidence":null}]